pystrtools/__init__.py
pystrtools/analysis.py
pystrtools/checks.py
pystrtools/consts.py
strtools/__init__.py
strtools/checks.py
strtools/consts.py
pystrtools-0.1.2.dist-info/LICENSE
pystrtools-0.1.2.dist-info/METADATA
pystrtools-0.1.2.dist-info/WHEEL
pystrtools-0.1.2.dist-info/top_level.txt
pystrtools-0.1.2.dist-info/RECORD
